source/upcounter.v
// -- Simple Verilog Counter -- //
// This file contains a simple 4 bit verilog up-counter.
// This counter has a synchronous reset.
// code inspired by: https://riptutorial.com/verilog/example/8307/simple-counter

module upcounter (clk,rst_n,count);

input clk;
input rst_n;
output reg [3:0] count;

always @(posedge clk) begin
    if (!rst_n)
        count <= 4'd0;
    else
        count <= count + 4'd1;
end

endmodule

source/upcounter_tb.v
// -- Test Bench 4 bit Upcounter -- //

`timescale 1ns / 1ns

module upcounter_tb();

reg clk, reset;
wire [3:0] count;

upcounter dut(clk, reset, count);

always begin
    #5 clk = ~clk;
end

initial begin 
    $dumpfile("upcounter.vcd");
    $dumpvars(0,upcounter_tb);
    clk = 0; reset = 0;
    #20;
    reset = 1;
    #10 if (count == 4'd1) begin
        $display($time,"ns; Value of counter is correct: %b", count);
    end
    #40 reset = 0;
    #20 reset = 1;
end 

initial begin
    #200;
    $display("simulation done!");
    $finish;
end

endmodule

simulations/upcounter.vcd
$date
	Fri Nov 11 11:29:46 2022
$end
$version
	Icarus Verilog
$end
$timescale
	1ns
$end
$scope module upcounter_tb $end
$var wire 4 ! count [3:0] $end
$var reg 1 " clk $end
$var reg 1 # reset $end
$scope module dut $end
$var wire 1 " clk $end
$var wire 1 # rst_n $end
$var reg 4 $ count [3:0] $end
$upscope $end
$upscope $end
$enddefinitions $end
#0
$dumpvars
bx $
0#
0"
bx !
$end
#5
b0 !
b0 $
1"
#10
0"
#15
1"
#20
0"
1#
#25
b1 !
b1 $
1"
#30
0"
#35
b10 !
b10 $
1"
#40
0"
#45
b11 !
b11 $
1"
#50
0"
#55
b100 !
b100 $
1"
#60
0"
#65
b101 !
b101 $
1"
#70
0"
0#
#75
b0 !
b0 $
1"
#80
0"
#85
1"
#90
0"
1#
#95
b1 !
b1 $
1"
#100
0"
#105
b10 !
b10 $
1"
#110
0"
#115
b11 !
b11 $
1"
#120
0"
#125
b100 !
b100 $
1"
#130
0"
#135
b101 !
b101 $
1"
#140
0"
#145
b110 !
b110 $
1"
#150
0"
#155
b111 !
b111 $
1"
#160
0"
#165
b1000 !
b1000 $
1"
#170
0"
#175
b1001 !
b1001 $
1"
#180
0"
#185
b1010 !
b1010 $
1"
#190
0"
#195
b1011 !
b1011 $
1"
